protowire/__init__.py
protowire/commandline.py
protowire/grpc_frame.py
protowire/proto_decoding.py
protowire/protobuf.py
protowire/wire_type.py
protowire-1.2.1.dist-info/LICENSE
protowire-1.2.1.dist-info/METADATA
protowire-1.2.1.dist-info/WHEEL
protowire-1.2.1.dist-info/entry_points.txt
protowire-1.2.1.dist-info/top_level.txt
protowire-1.2.1.dist-info/RECORD
