Metadata-Version: 2.1
Name: protowire
Version: 1.2.1
Summary: Write protobuf messages & GRPC calls from the command line without the proto files
Home-page: https://github.com/oseiskar/protowire
Author: Otto Seiskari
License: MIT
Keywords: grpc protobuf commandline cli
Platform: UNKNOWN
Classifier: Development Status :: 5 - Production/Stable
Classifier: Intended Audience :: Developers
Classifier: License :: OSI Approved :: MIT License
Classifier: Programming Language :: Python :: 2
Classifier: Programming Language :: Python :: 2.7
Classifier: Programming Language :: Python :: 3
Classifier: Programming Language :: Python :: 3.6
Provides-Extra: dev
Requires-Dist: nose ; extra == 'dev'
Requires-Dist: pylint ; extra == 'dev'
Requires-Dist: check-manifest ; extra == 'dev'
Provides-Extra: grpc
Requires-Dist: grcpio ; extra == 'grpc'
